<metadata xml:lang="pt"><Esri><CreaDate>20201202</CreaDate><CreaTime>15503900</CreaTime><ArcGISFormat>1.0</ArcGISFormat><SyncOnce>FALSE</SyncOnce><DataProperties><lineage><Process ToolSource="c:\program files (x86)\arcgis\desktop10.8\ArcToolbox\Toolboxes\Data Management Tools.tbx\DeleteField" Date="20201202" Time="155039" Name="" export="">DeleteField "C:\Projetos\PDE\Base cartográfica\solarpv_ope_PDE2030.shp" Id;Leilão;Município;UF;Subsistema;PotVend_MW;Bioma;Semiárido;Pop_munici;IDH_munici;Status;Inicio_sup;Obs;Tipo_atuac;CEG;FID_novo</Process><Process ToolSource="c:\program files (x86)\arcgis\desktop10.8\ArcToolbox\Toolboxes\Data Management Tools.tbx\AlterField" Date="20201208" Time="115925" Name="" export="">AlterField solarpv_ope_PDE2030 Nome_Empre nome Nome TEXT 150 NULLABLE false</Process><Process ToolSource="c:\program files (x86)\arcgis\desktop10.8\ArcToolbox\Toolboxes\Data Management Tools.tbx\AlterField" Date="20201208" Time="115947" Name="" export="">AlterField solarpv_ope_PDE2030 Proprietar propriet Proprietário TEXT 100 NULLABLE false</Process><Process ToolSource="c:\program files (x86)\arcgis\desktop10.8\ArcToolbox\Toolboxes\Data Management Tools.tbx\AlterField" Date="20201208" Time="120011" Name="" export="">AlterField solarpv_ope_PDE2030 Potencia potencia "Potência (kW)" DOUBLE 8 NULLABLE false</Process><Process ToolSource="c:\program files (x86)\arcgis\desktop10.8\ArcToolbox\Toolboxes\Data Management Tools.tbx\AlterField" Date="20201208" Time="120035" Name="" export="">AlterField solarpv_ope_PDE2030 Inicio_op ini_oper "Início da operação" DATE 8 NULLABLE false</Process><Process ToolSource="c:\program files (x86)\arcgis\desktop10.8\ArcToolbox\Toolboxes\Data Management Tools.tbx\AlterField" Date="20201208" Time="120054" Name="" export="">AlterField solarpv_ope_PDE2030 CEG_novo ceg CEG TEXT 254 NULLABLE false</Process><Process ToolSource="c:\program files (x86)\arcgis\desktop10.8\ArcToolbox\Toolboxes\Data Management Tools.tbx\AlterField" Date="20201208" Time="120133" Name="" export="">AlterField solarpv_ope_PDE2030 Potencia potencia "Potência (kW)" DOUBLE 8 NULLABLE false</Process><Process ToolSource="c:\program files (x86)\arcgis\desktop10.7\ArcToolbox\Toolboxes\Conversion Tools.tbx\FeatureClassToFeatureClass" Date="20201216" Time="144156">FeatureClassToFeatureClass solarpv_ope_PDE2030 "Database Connections\Gisuser PRD2 Connection to sqlclmixedprd - PRD2.sde\EPEGIS02.DBO.WebmapSistemaEletricoExistente" UFV_Existentes # "nome "Nome" true true false 150 Text 0 0 ,First,#,solarpv_ope_PDE2030,nome,-1,-1;propriet "Proprietário" true true false 100 Text 0 0 ,First,#,solarpv_ope_PDE2030,propriet,-1,-1;Potencia "Potência (kW)" true true false 8 Double 0 0 ,First,#,solarpv_ope_PDE2030,Potencia,-1,-1;ini_oper "Início da operação" true true false 8 Date 0 0 ,First,#,solarpv_ope_PDE2030,ini_oper,-1,-1;ceg "CEG" true true false 254 Text 0 0 ,First,#,solarpv_ope_PDE2030,ceg,-1,-1" #</Process></lineage><itemProps><itemName Sync="TRUE">UFV___Base_Existente</itemName><imsContentType Sync="TRUE" export="False">002</imsContentType><itemLocation><linkage Sync="TRUE">file://\\VSVR-AGSPRD2\E\arcgisserver\directories\arcgisjobs\sma\downloadwebmapepe_gpserver\jc65dd3f746f14c63b4857f6276e3980a\scratch\zipfolder\UFV___Base_Existente.shp</linkage><protocol Sync="TRUE">Local Area Network</protocol></itemLocation><nativeExtBox><westBL Sync="TRUE">-53.307333</westBL><eastBL Sync="TRUE">-35.958003</eastBL><southBL Sync="TRUE">-27.687694</southBL><northBL Sync="TRUE">-3.984734</northBL><exTypeCode Sync="TRUE">1</exTypeCode></nativeExtBox><itemSize Sync="TRUE">0.000</itemSize></itemProps><coordRef><type Sync="TRUE">Geographic</type><geogcsn Sync="TRUE">GCS_SIRGAS_2000</geogcsn><csUnits Sync="TRUE">Angular Unit: Degree (0.017453)</csUnits><peXml Sync="TRUE">&lt;GeographicCoordinateSystem xsi:type='typens:GeographicCoordinateSystem' xmlns:xsi='http://www.w3.org/2001/XMLSchema-instance' xmlns:xs='http://www.w3.org/2001/XMLSchema' xmlns:typens='http://www.esri.com/schemas/ArcGIS/10.7'&gt;&lt;WKT&gt;GEOGCS[&amp;quot;GCS_SIRGAS_2000&amp;quot;,DATUM[&amp;quot;D_SIRGAS_2000&amp;quot;,SPHEROID[&amp;quot;GRS_1980&amp;quot;,6378137.0,298.257222101]],PRIMEM[&amp;quot;Greenwich&amp;quot;,0.0],UNIT[&amp;quot;Degree&amp;quot;,0.0174532925199433],AUTHORITY[&amp;quot;EPSG&amp;quot;,4674]]&lt;/WKT&gt;&lt;XOrigin&gt;-400&lt;/XOrigin&gt;&lt;YOrigin&gt;-400&lt;/YOrigin&gt;&lt;XYScale&gt;11258999068426.238&lt;/XYScale&gt;&lt;ZOrigin&gt;-100000&lt;/ZOrigin&gt;&lt;ZScale&gt;10000&lt;/ZScale&gt;&lt;MOrigin&gt;-100000&lt;/MOrigin&gt;&lt;MScale&gt;10000&lt;/MScale&gt;&lt;XYTolerance&gt;8.9831528411952133e-09&lt;/XYTolerance&gt;&lt;ZTolerance&gt;0.001&lt;/ZTolerance&gt;&lt;MTolerance&gt;0.001&lt;/MTolerance&gt;&lt;HighPrecision&gt;true&lt;/HighPrecision&gt;&lt;LeftLongitude&gt;-180&lt;/LeftLongitude&gt;&lt;WKID&gt;4674&lt;/WKID&gt;&lt;LatestWKID&gt;4674&lt;/LatestWKID&gt;&lt;/GeographicCoordinateSystem&gt;</peXml></coordRef></DataProperties><SyncDate>20210310</SyncDate><SyncTime>12192400</SyncTime><ModDate>20210310</ModDate><ModTime>12192400</ModTime><scaleRange><minScale>150000000</minScale><maxScale>5000</maxScale></scaleRange><ArcGISProfile>NAP</ArcGISProfile></Esri><dataIdInfo><envirDesc Sync="TRUE"> Version 6.2 (Build 9200) ; Esri ArcGIS 10.7.1.11595</envirDesc><dataLang><languageCode value="eng" Sync="TRUE"/><countryCode value="USA" Sync="TRUE"/></dataLang><idCitation xmlns=""><resTitle Sync="FALSE">UFV – Base Existente</resTitle><presForm xmlns=""><PresFormCd value="005" Sync="TRUE"/></presForm><date><createDate>2020-09-11T00:00:00</createDate></date></idCitation><spatRpType><SpatRepTypCd value="001" Sync="TRUE"/></spatRpType><dataExt><geoEle xmlns=""><GeoBndBox esriExtentType="search"><exTypeCode Sync="TRUE">1</exTypeCode><westBL Sync="TRUE">-53.307333</westBL><eastBL Sync="TRUE">-35.958003</eastBL><northBL Sync="TRUE">-3.984734</northBL><southBL Sync="TRUE">-27.687694</southBL></GeoBndBox></geoEle></dataExt><idPurp>Empreendimentos de geração solar fotovoltaica em operação</idPurp><idAbs>&lt;DIV STYLE="text-align:Left;"&gt;&lt;DIV&gt;&lt;P&gt;&lt;SPAN STYLE="font-weight:bold;"&gt;&lt;SPAN&gt;Empreendimentos de geração solar fotovoltaica em operação&lt;/SPAN&gt;&lt;/SPAN&gt;&lt;/P&gt;&lt;/DIV&gt;&lt;/DIV&gt;</idAbs><idCredit>EPE, ONS, MME, CCEE, ANEEL
2020-09-11; criação</idCredit><searchKeys><keyword>Geração Solar Fotovoltaica; Sistema Existente</keyword></searchKeys><tpCat><TopicCatCd value="019"/></tpCat></dataIdInfo><mdLang><languageCode value="eng" Sync="TRUE"/><countryCode value="USA" Sync="TRUE"/></mdLang><distInfo xmlns=""><distFormat xmlns=""><formatName Sync="TRUE">Shapefile</formatName><formatVer>vetor</formatVer></distFormat><distTranOps><transSize Sync="TRUE">0.000</transSize></distTranOps></distInfo><mdHrLv><ScopeCd value="005" Sync="TRUE"/></mdHrLv><mdHrLvName Sync="TRUE">dataset</mdHrLvName><refSysInfo><RefSystem dimension="temporal"><refSysID xmlns=""><identCode code="4674" Sync="TRUE"/><idCodeSpace Sync="TRUE">EPSG</idCodeSpace><idVersion Sync="TRUE">7.8.3(9.2.0)</idVersion></refSysID></RefSystem></refSysInfo><spatRepInfo><VectSpatRep><geometObjs Name="UFV___Base_Existente"><geoObjTyp><GeoObjTypCd value="004" Sync="TRUE"></GeoObjTypCd></geoObjTyp><geoObjCnt Sync="TRUE">0</geoObjCnt></geometObjs><topLvl><TopoLevCd value="001" Sync="TRUE"></TopoLevCd></topLvl></VectSpatRep></spatRepInfo><spdoinfo><ptvctinf><esriterm Name="UFV___Base_Existente"><efeatyp Sync="TRUE">Simple</efeatyp><efeageom code="1" Sync="TRUE"></efeageom><esritopo Sync="TRUE">FALSE</esritopo><efeacnt Sync="TRUE">0</efeacnt><spindex Sync="TRUE">FALSE</spindex><linrefer Sync="TRUE">FALSE</linrefer></esriterm></ptvctinf></spdoinfo><eainfo><detailed xmlns="" Name="UFV___Base_Existente"><enttyp><enttypl Sync="TRUE">UFV___Base_Existente</enttypl><enttypt Sync="TRUE">Feature Class</enttypt><enttypc Sync="TRUE">0</enttypc></enttyp><attr><attrlabl Sync="TRUE">FID</attrlabl><attalias Sync="TRUE">FID</attalias><attrtype Sync="TRUE">OID</attrtype><attwidth Sync="TRUE">4</attwidth><atprecis Sync="TRUE">0</atprecis><attscale Sync="TRUE">0</attscale><attrdef Sync="TRUE">Internal feature number.</attrdef><attrdefs Sync="TRUE">Esri</attrdefs><attrdomv><udom Sync="TRUE">Sequential unique whole numbers that are automatically generated.</udom></attrdomv></attr><attr xmlns=""><attrlabl Sync="TRUE">Shape</attrlabl><attalias Sync="TRUE">Shape</attalias><attrtype Sync="TRUE">Geometry</attrtype><attwidth Sync="TRUE">0</attwidth><atprecis Sync="TRUE">0</atprecis><attscale Sync="TRUE">0</attscale><attrdef Sync="TRUE">Feature geometry.</attrdef><attrdefs Sync="TRUE">Esri</attrdefs><attrdomv><udom Sync="TRUE">Coordinates defining the features.</udom></attrdomv></attr><attr xmlns=""><attrlabl Sync="TRUE">nome</attrlabl><attalias Sync="TRUE">nome</attalias><attrtype Sync="TRUE">String</attrtype><attwidth Sync="TRUE">150</attwidth><atprecis Sync="TRUE">0</atprecis><attscale Sync="TRUE">0</attscale><attrdef>Nome da usina</attrdef><attrdefs>EPE</attrdefs></attr><attr xmlns=""><attrlabl Sync="TRUE">propriet</attrlabl><attalias Sync="TRUE">propriet</attalias><attrtype Sync="TRUE">String</attrtype><attwidth Sync="TRUE">100</attwidth><atprecis Sync="TRUE">0</atprecis><attscale Sync="TRUE">0</attscale><attrdef>Proprietário da usina</attrdef><attrdefs>EPE</attrdefs></attr><attr xmlns=""><attrlabl Sync="TRUE">Potencia</attrlabl><attalias Sync="TRUE">Potencia</attalias><attrtype Sync="TRUE">Double</attrtype><attwidth Sync="TRUE">19</attwidth><atprecis Sync="TRUE">18</atprecis><attscale Sync="TRUE">8</attscale><attrdef>Capacidade instalada do empreendimento</attrdef><attrdefs>EPE</attrdefs></attr><attr xmlns=""><attrlabl Sync="TRUE">ini_oper</attrlabl><attalias Sync="TRUE">ini_oper</attalias><attrtype Sync="TRUE">Date</attrtype><attwidth Sync="TRUE">8</attwidth><atprecis Sync="TRUE">0</atprecis><attscale Sync="TRUE">0</attscale><attrdef>Data de entrada em operação do empreendimento</attrdef><attrdefs>EPE</attrdefs></attr><attr xmlns=""><attrlabl Sync="TRUE">ceg</attrlabl><attalias Sync="TRUE">ceg</attalias><attrtype Sync="TRUE">String</attrtype><attwidth Sync="TRUE">254</attwidth><atprecis Sync="TRUE">0</atprecis><attscale Sync="TRUE">0</attscale><attrdef>Código único de empreendimento de geração</attrdef><attrdefs>EPE</attrdefs></attr><attr><attrlabl Sync="TRUE">created_us</attrlabl><attalias Sync="TRUE">created_us</attalias><attrtype Sync="TRUE">String</attrtype><attwidth Sync="TRUE">254</attwidth><atprecis Sync="TRUE">0</atprecis><attscale Sync="TRUE">0</attscale></attr><attr><attrlabl Sync="TRUE">created_da</attrlabl><attalias Sync="TRUE">created_da</attalias><attrtype Sync="TRUE">Date</attrtype><attwidth Sync="TRUE">8</attwidth><atprecis Sync="TRUE">0</atprecis><attscale Sync="TRUE">0</attscale></attr><attr><attrlabl Sync="TRUE">last_edite</attrlabl><attalias Sync="TRUE">last_edite</attalias><attrtype Sync="TRUE">String</attrtype><attwidth Sync="TRUE">254</attwidth><atprecis Sync="TRUE">0</atprecis><attscale Sync="TRUE">0</attscale></attr><attr><attrlabl Sync="TRUE">last_edi_1</attrlabl><attalias Sync="TRUE">last_edi_1</attalias><attrtype Sync="TRUE">Date</attrtype><attwidth Sync="TRUE">8</attwidth><atprecis Sync="TRUE">0</atprecis><attscale Sync="TRUE">0</attscale></attr></detailed></eainfo><mdDateSt Sync="TRUE">20210310</mdDateSt><mdFileID>0C188CF0-93CE-4D87-9F84-B2A130928194</mdFileID><mdChar><CharSetCd value="004"/></mdChar><mdContact xmlns=""><rpIndName>sic@epe.gov.br</rpIndName><rpOrgName>EPE</rpOrgName><role><RoleCd value="011"/></role></mdContact></metadata>
